boltzjobs/__init__.py
boltzjobs/__main__.py
boltzjobs/components.py
boltzjobs/jobs.py
boltzjobs/utils.py
boltzjobs-0.2.0.dist-info/METADATA
boltzjobs-0.2.0.dist-info/WHEEL
boltzjobs-0.2.0.dist-info/licenses/LICENSE.txt
boltzjobs-0.2.0.dist-info/RECORD
