Metadata-Version: 2.4
Name: boltzjobs
Version: 0.2.0
Summary: Module for defining molecular components, modifications, and job configurations for Boltz-2
Project-URL: Homepage, https://github.com/ugSUBMARINE/boltzjobs
Project-URL: Documentation, https://github.com/ugSUBMARINE/boltzjobs#readme
Project-URL: Repository, https://github.com/ugSUBMARINE/boltzjobs.git
Project-URL: Bug Tracker, https://github.com/ugSUBMARINE/boltzjobs/issues
Project-URL: Changelog, https://github.com/ugSUBMARINE/boltzjobs/releases
Author-email: Karl Gruber <gammaturn@gmail.com>
Maintainer-email: Karl Gruber <gammaturn@gmail.com>
License: MIT
License-File: LICENSE.txt
Keywords: Boltz-2,YAML,bioinformatics,molecular biology,protein modeling,structural biology
Classifier: License :: OSI Approved :: MIT License
Classifier: Operating System :: OS Independent
Classifier: Programming Language :: Python :: 3
Classifier: Programming Language :: Python :: 3.11
Classifier: Programming Language :: Python :: 3.12
Classifier: Programming Language :: Python :: 3.13
Classifier: Programming Language :: Python :: 3.14
Requires-Python: >=3.11
Requires-Dist: pyyaml>=6.0.2
